{
	"title": "당신의 집중력은 고작 40초 | 하이퍼포커스 by 크리스 베일리",
	"youtube_url": "'https://www.youtube.com/watch?v=xJdv4rwFvig&list=PLKrfWbGO7784zkTtIJpBWY_PJcF-_uzye&index=11&t=0s'",
	"lang_code": "ko",
	"font_size": 30,
	"file_name": "40",
	"nosub_opt": true,
	"thumbnail": "https://i.ytimg.com/vi/xJdv4rwFvig/maxresdefault.jpg",
	"frame_infos": [
		{
			"frame_num": 0,
			"img_path": "/home/ubuntu/project/youtube_capture/imgs/400.jpg",
			"time_info": 3.0,
			"script": "40초 컴퓨터 앞에 앉아 일하기 시작한 지 40초 만에",
			"hash": null,
			"sub_hash": "ffefcfff818181ff",
			"usage": true
		},
		{
			"frame_num": 1,
			"img_path": "/home/ubuntu/project/youtube_capture/imgs/401.jpg",
			"time_info": 7.5,
			"script": "우리는 주의를 다른 데로 돌립니다",
			"hash": null,
			"sub_hash": "ffffffff818181ff",
			"usage": true
		},
		{
			"frame_num": 2,
			"img_path": "/home/ubuntu/project/youtube_capture/imgs/402.jpg.dupli.jpg",
			"time_info": 11.0,
			"script": "4 10초만 지나면 갑자기 궁금한게 떠오르고",
			"hash": null,
			"sub_hash": "ffffffff818181ff",
			"usage": false
		},
		{
			"frame_num": 3,
			"img_path": "/home/ubuntu/project/youtube_capture/imgs/403.jpg.dupli.jpg",
			"time_info": 15.5,
			"script": "인터넷 포털을 켜고 싶고 걱정 허리가 생각나며 스마트폰을 확인하고 싶어",
			"hash": null,
			"sub_hash": "ffffffff818181ff",
			"usage": false
		},
		{
			"frame_num": 4,
			"img_path": "/home/ubuntu/project/youtube_capture/imgs/404.jpg",
			"time_info": 19.0,
			"script": "집니다",
			"hash": null,
			"sub_hash": "0000000000000000",
			"usage": true
		},
		{
			"frame_num": 5,
			"img_path": "/home/ubuntu/project/youtube_capture/imgs/405.jpg",
			"time_info": 22.5,
			"script": "오늘날 우리는 주위를 방해하는 것이 유리 없이 많은 세상을 살고 있습니다",
			"hash": null,
			"sub_hash": "ffffdfff818181ff",
			"usage": true
		},
		{
			"frame_num": 6,
			"img_path": "/home/ubuntu/project/youtube_capture/imgs/406.jpg.dupli.jpg",
			"time_info": 28.0,
			"script": "주력 에 관한 현장 연구에 따르면 사람들은 평균 40 초 마다 일을",
			"hash": null,
			"sub_hash": "ffffdfff818181ff",
			"usage": false
		},
		{
			"frame_num": 7,
			"img_path": "/home/ubuntu/project/youtube_capture/imgs/407.jpg.dupli.jpg",
			"time_info": 31.5,
			"script": "멈추고",
			"hash": null,
			"sub_hash": "ffffdfff818181ff",
			"usage": false
		},
		{
			"frame_num": 8,
			"img_path": "/home/ubuntu/project/youtube_capture/imgs/408.jpg.dupli.jpg",
			"time_info": 34.0,
			"script": "하루 500 66번 컴퓨터 프로그램을 바꿈 하시라고",
			"hash": null,
			"sub_hash": "ffffdfdf818181ff",
			"usage": false
		},
		{
			"frame_num": 9,
			"img_path": "/home/ubuntu/project/youtube_capture/imgs/409.jpg.dupli.jpg",
			"time_info": 39.0,
			"script": "페이스북 사용자라면 하루에 타임라인을 평 구 38 을 확인합니다",
			"hash": null,
			"sub_hash": "ffffdfdf818181ff",
			"usage": false
		},
		{
			"frame_num": 10,
			"img_path": "/home/ubuntu/project/youtube_capture/imgs/4010.jpg",
			"time_info": 44.0,
			"script": "더 많은 일을 동시에 저리 아르고 외치지만",
			"hash": null,
			"sub_hash": "ffffffff818181ff",
			"usage": true
		},
		{
			"frame_num": 11,
			"img_path": "/home/ubuntu/project/youtube_capture/imgs/4011.jpg.dupli.jpg",
			"time_info": 47.5,
			"script": "중요한 일 단 한가지도 끝내지 못합니다",
			"hash": null,
			"sub_hash": "ffffffff818181ff",
			"usage": false
		},
		{
			"frame_num": 12,
			"img_path": "/home/ubuntu/project/youtube_capture/imgs/4012.jpg",
			"time_info": 51.0,
			"script": "이런 우리에게 필요한 것이 하이퍼 포커스 입니다",
			"hash": null,
			"sub_hash": "f9f9f1f1818181ff",
			"usage": true
		},
		{
			"frame_num": 13,
			"img_path": "/home/ubuntu/project/youtube_capture/imgs/4013.jpg",
			"time_info": 54.5,
			"script": "하이퍼 포커스 란 의도와 목적을 가지고",
			"hash": null,
			"sub_hash": "b9b9b9b98181833f",
			"usage": true
		},
		{
			"frame_num": 14,
			"img_path": "/home/ubuntu/project/youtube_capture/imgs/4014.jpg",
			"time_info": 58.5,
			"script": "중요한 일 하나에만 깊게 집중하는 상태를 뜻합니다",
			"hash": null,
			"sub_hash": "f9f9f1f1818181ff",
			"usage": true
		},
		{
			"frame_num": 15,
			"img_path": "/home/ubuntu/project/youtube_capture/imgs/4015.jpg",
			"time_info": 63.5,
			"script": "3 사서 전문가 로 유명한 크리스 밸리가 점점 3만에 지나 자신을 위해",
			"hash": null,
			"sub_hash": "f9f9f9f9818181ff",
			"usage": true
		},
		{
			"frame_num": 16,
			"img_path": "/home/ubuntu/project/youtube_capture/imgs/4016.jpg.dupli.jpg",
			"time_info": 68.0,
			"script": "집중 너가 뭐 랩에 대해 영과 책입니다",
			"hash": null,
			"sub_hash": "b9f9f9f9818181ff",
			"usage": false
		},
		{
			"frame_num": 17,
			"img_path": "/home/ubuntu/project/youtube_capture/imgs/4017.jpg",
			"time_info": 72.5,
			"script": "일을 제대로 하기 위해서 더 창의적이고 3 사적인 하루를 보내기 위해서",
			"hash": null,
			"sub_hash": "fffefeff818081ff",
			"usage": true
		},
		{
			"frame_num": 18,
			"img_path": "/home/ubuntu/project/youtube_capture/imgs/4018.jpg",
			"time_info": 77.5,
			"script": "할 법 5 컷에 대해 같이 알아봅시다",
			"hash": null,
			"sub_hash": "fffffff3818181ff",
			"usage": true
		},
		{
			"frame_num": 19,
			"img_path": "/home/ubuntu/project/youtube_capture/imgs/4019.jpg",
			"time_info": 81.5,
			"script": "30초 정도 걸리는 간단한 어찌 있습니다",
			"hash": null,
			"sub_hash": "ffffffff818181ff",
			"usage": true
		},
		{
			"frame_num": 20,
			"img_path": "/home/ubuntu/project/youtube_capture/imgs/4020.jpg",
			"time_info": 86.0,
			"script": "다음 질문에 솔직하게 답해 보세요 당신의 하루 동안 얼마나 자주 어디에",
			"hash": null,
			"sub_hash": "0000000000000000",
			"usage": true
		},
		{
			"frame_num": 21,
			"img_path": "/home/ubuntu/project/youtube_capture/imgs/4021.jpg",
			"time_info": 90.5,
			"script": "집중할 재를 선택한 아요",
			"hash": null,
			"sub_hash": "ffffffff818181ff",
			"usage": true
		},
		{
			"frame_num": 22,
			"img_path": "/home/ubuntu/project/youtube_capture/imgs/4022.jpg",
			"time_info": 94.5,
			"script": "다시 말에 무엇을 하고 싶고 그것을 언제 할지 미리 결정하는 데 투자하는",
			"hash": null,
			"sub_hash": "f3f3f3f3818181e3",
			"usage": true
		},
		{
			"frame_num": 23,
			"img_path": "/home/ubuntu/project/youtube_capture/imgs/4023.jpg",
			"time_info": 98.5,
			"script": "시간이 얼마큼 인가요",
			"hash": null,
			"sub_hash": "ffffffff818181ff",
			"usage": true
		},
		{
			"frame_num": 24,
			"img_path": "/home/ubuntu/project/youtube_capture/imgs/4024.jpg",
			"time_info": 102.0,
			"script": "대부분의 사람이 이 질문에 답을 자라지 못합니다",
			"hash": null,
			"sub_hash": "efefefef818181ff",
			"usage": true
		},
		{
			"frame_num": 25,
			"img_path": "/home/ubuntu/project/youtube_capture/imgs/4025.jpg.dupli.jpg",
			"time_info": 107.5,
			"script": "무엇을 집중 할지 선택하는 시간이 없거나 있다 하더라도 잘 나의 불과하죠",
			"hash": null,
			"sub_hash": "efefefef818181ff",
			"usage": false
		},
		{
			"frame_num": 26,
			"img_path": "/home/ubuntu/project/youtube_capture/imgs/4026.jpg",
			"time_info": 112.5,
			"script": "자동 조정 기능을 켜고 있는 것과 같습니다",
			"hash": null,
			"sub_hash": "ffffffff818181ff",
			"usage": true
		},
		{
			"frame_num": 27,
			"img_path": "/home/ubuntu/project/youtube_capture/imgs/4027.jpg.dupli.jpg",
			"time_info": 117.0,
			"script": "내 계획과 루 2대로 하루를 보내는 것이 아니라 습관적으로 웹브라우저 와",
			"hash": null,
			"sub_hash": "ffffffff818181ff",
			"usage": false
		},
		{
			"frame_num": 28,
			"img_path": "/home/ubuntu/project/youtube_capture/imgs/4028.jpg.dupli.jpg",
			"time_info": 120.5,
			"script": "sns 를 10국",
			"hash": null,
			"sub_hash": "ffffffff818181ff",
			"usage": false
		},
		{
			"frame_num": 29,
			"img_path": "/home/ubuntu/project/youtube_capture/imgs/4029.jpg.dupli.jpg",
			"time_info": 123.0,
			"script": "이메일이 오면 하던 일을 멈추고 거기에 답하고",
			"hash": null,
			"sub_hash": "fdffffff818181ff",
			"usage": false
		},
		{
			"frame_num": 30,
			"img_path": "/home/ubuntu/project/youtube_capture/imgs/4030.jpg.dupli.jpg",
			"time_info": 127.5,
			"script": "중요한 일보다 지금 당장 눈에 들어 오늘부터 처리합니다",
			"hash": null,
			"sub_hash": "fdffffff818181ff",
			"usage": false
		},
		{
			"frame_num": 31,
			"img_path": "/home/ubuntu/project/youtube_capture/imgs/4031.jpg.dupli.jpg",
			"time_info": 132.5,
			"script": "주변 환경에서 가장 긴급하고 자극적인 것이 가장 중요한 일은 경우는",
			"hash": null,
			"sub_hash": "ffffffff818181ff",
			"usage": false
		},
		{
			"frame_num": 32,
			"img_path": "/home/ubuntu/project/youtube_capture/imgs/4032.jpg.dupli.jpg",
			"time_info": 138.0,
			"script": "드물기 에 우리는 자도 조적 기능을 끄고 일해야 합니다",
			"hash": null,
			"sub_hash": "ffffffff818181ff",
			"usage": false
		},
		{
			"frame_num": 33,
			"img_path": "/home/ubuntu/project/youtube_capture/imgs/4033.jpg",
			"time_info": 143.5,
			"script": "자동 조소 상태와 반대되는 것이 의도를 갖고 일하는 것입니다",
			"hash": null,
			"sub_hash": "e7e7e7e7818181e7",
			"usage": true
		},
		{
			"frame_num": 34,
			"img_path": "/home/ubuntu/project/youtube_capture/imgs/4034.jpg",
			"time_info": 147.5,
			"script": "왜 이 일을 해야 하는지 의식하면서",
			"hash": null,
			"sub_hash": "ffffffff818181ff",
			"usage": true
		},
		{
			"frame_num": 35,
			"img_path": "/home/ubuntu/project/youtube_capture/imgs/4035.jpg.dupli.jpg",
			"time_info": 150.5,
			"script": "목적을 생각하면서 이라는 거죠",
			"hash": null,
			"sub_hash": "ffffffff818181ff",
			"usage": false
		},
		{
			"frame_num": 36,
			"img_path": "/home/ubuntu/project/youtube_capture/imgs/4036.jpg.dupli.jpg",
			"time_info": 153.5,
			"script": "의도는 하이퍼 포커스 를 이끄는 중요한 조건입니다",
			"hash": null,
			"sub_hash": "ffffffff818181ff",
			"usage": false
		},
		{
			"frame_num": 37,
			"img_path": "/home/ubuntu/project/youtube_capture/imgs/4037.jpg",
			"time_info": 155.5,
			"script": "[음악]",
			"hash": null,
			"sub_hash": "ffffefef818181cf",
			"usage": true
		},
		{
			"frame_num": 38,
			"img_path": "/home/ubuntu/project/youtube_capture/imgs/4038.jpg",
			"time_info": 158.5,
			"script": "의도가 있으면 우선순위를 정할 수 있고 내가 편한 일을 하고 있다는",
			"hash": null,
			"sub_hash": "efefe3ff818181ff",
			"usage": true
		},
		{
			"frame_num": 39,
			"img_path": "/home/ubuntu/project/youtube_capture/imgs/4039.jpg.dupli.jpg",
			"time_info": 163.5,
			"script": "생각에 마음이 차분해 지면서 끝까지 지쳐 할 수 있게 됩니다",
			"hash": null,
			"sub_hash": "efefe3ff818181ff",
			"usage": false
		},
		{
			"frame_num": 40,
			"img_path": "/home/ubuntu/project/youtube_capture/imgs/4040.jpg",
			"time_info": 168.0,
			"script": "그렇다면 무엇에 의도적으로 집중 해야 할까요",
			"hash": null,
			"sub_hash": "ffffffff818181ff",
			"usage": true
		},
		{
			"frame_num": 41,
			"img_path": "/home/ubuntu/project/youtube_capture/imgs/4041.jpg",
			"time_info": 171.5,
			"script": "이 결정을 도와줄 표가 하나 있습니다",
			"hash": null,
			"sub_hash": "ffffff81818181ff",
			"usage": true
		},
		{
			"frame_num": 42,
			"img_path": "/home/ubuntu/project/youtube_capture/imgs/4042.jpg.dupli.jpg",
			"time_info": 174.0,
			"script": "가루 축을 과제 매력도 라 정하고",
			"hash": null,
			"sub_hash": "ffffff80818181ff",
			"usage": false
		},
		{
			"frame_num": 43,
			"img_path": "/home/ubuntu/project/youtube_capture/imgs/4043.jpg.dupli.jpg",
			"time_info": 177.0,
			"script": "새로 축을 관해 생산성을 해봅시다",
			"hash": null,
			"sub_hash": "ffffff80818181ff",
			"usage": false
		},
		{
			"frame_num": 44,
			"img_path": "/home/ubuntu/project/youtube_capture/imgs/4044.jpg.dupli.jpg",
			"time_info": 181.0,
			"script": "왼쪽에는 에러 저 지는 않지만 3사 저 낼",
			"hash": null,
			"sub_hash": "ffffff80818181ff",
			"usage": false
		},
		{
			"frame_num": 45,
			"img_path": "/home/ubuntu/project/youtube_capture/imgs/4045.jpg.dupli.jpg",
			"time_info": 185.5,
			"script": "즉 필요한 일이라 할 수 있습니다 보고서 작성 부서 회의 업무 전화 등이",
			"hash": null,
			"sub_hash": "ffffff80818181ff",
			"usage": false
		},
		{
			"frame_num": 46,
			"img_path": "/home/ubuntu/project/youtube_capture/imgs/4046.jpg",
			"time_info": 189.5,
			"script": "이곳에 속하죠",
			"hash": null,
			"sub_hash": "ffffbd80fcffffff",
			"usage": true
		},
		{
			"frame_num": 47,
			"img_path": "/home/ubuntu/project/youtube_capture/imgs/4047.jpg",
			"time_info": 192.5,
			"script": "왼쪽 비튼 빛의 사적이고 매력 저 시도하는 1",
			"hash": null,
			"sub_hash": "ffffff80818181ff",
			"usage": true
		},
		{
			"frame_num": 48,
			"img_path": "/home/ubuntu/project/youtube_capture/imgs/4048.jpg.dupli.jpg",
			"time_info": 196.5,
			"script": "즉 불필요한 일입니다 책상에 있는 서로 정리하게",
			"hash": null,
			"sub_hash": "ffffff80818181ff",
			"usage": false
		},
		{
			"frame_num": 49,
			"img_path": "/home/ubuntu/project/youtube_capture/imgs/4049.jpg",
			"time_info": 200.5,
			"script": "의미없는 눅스 확인하기 를 예로 들 수 있죠",
			"hash": null,
			"sub_hash": "dfdf9f80818181ff",
			"usage": true
		},
		{
			"frame_num": 50,
			"img_path": "/home/ubuntu/project/youtube_capture/imgs/4050.jpg.dupli.jpg",
			"time_info": 205.0,
			"script": "중요한 일을 하기 싫어 미루고 싶을 때 우리는 불편한 일을 하면서 바쁜",
			"hash": null,
			"sub_hash": "dfdf9f80818181ff",
			"usage": false
		},
		{
			"frame_num": 51,
			"img_path": "/home/ubuntu/project/youtube_capture/imgs/4051.jpg",
			"time_info": 209.0,
			"script": "척을 하곤 합니다",
			"hash": null,
			"sub_hash": "8f8f8d80fcffffff",
			"usage": true
		},
		{
			"frame_num": 52,
			"img_path": "/home/ubuntu/project/youtube_capture/imgs/4052.jpg",
			"time_info": 212.5,
			"script": "매력적이며 서 비 스 사적인 일이라 주위를 빼앗는 일로 생산성을",
			"hash": null,
			"sub_hash": "d3f3f181c18181f3",
			"usage": true
		},
		{
			"frame_num": 53,
			"img_path": "/home/ubuntu/project/youtube_capture/imgs/4053.jpg",
			"time_info": 216.0,
			"script": "빨아들이는 블랙홀이 입니다",
			"hash": null,
			"sub_hash": "dfdf9f80818181ff",
			"usage": true
		},
		{
			"frame_num": 54,
			"img_path": "/home/ubuntu/project/youtube_capture/imgs/4054.jpg.dupli.jpg",
			"time_info": 218.5,
			"script": "소셜 미디어 카토 실시간 검색어",
			"hash": null,
			"sub_hash": "dfdf9780818181ff",
			"usage": false
		},
		{
			"frame_num": 55,
			"img_path": "/home/ubuntu/project/youtube_capture/imgs/4055.jpg",
			"time_info": 222.5,
			"script": "동료와의 잡 딴 등 집중을 방해하는 모든 것이 여기에 속합니다",
			"hash": null,
			"sub_hash": "dbdbd980818181ff",
			"usage": true
		},
		{
			"frame_num": 56,
			"img_path": "/home/ubuntu/project/youtube_capture/imgs/4056.jpg.dupli.jpg",
			"time_info": 225.5,
			"script": "[음악]",
			"hash": null,
			"sub_hash": "dbdbd980818181ff",
			"usage": false
		},
		{
			"frame_num": 57,
			"img_path": "/home/ubuntu/project/youtube_capture/imgs/4057.jpg.dupli.jpg",
			"time_info": 229.0,
			"script": "이런 활동한 주의 환기를 위해 조금을 괜찮았지만 조절이 필요합니다",
			"hash": null,
			"sub_hash": "dbdbd980818181ff",
			"usage": false
		},
		{
			"frame_num": 58,
			"img_path": "/home/ubuntu/project/youtube_capture/imgs/4058.jpg.dupli.jpg",
			"time_info": 233.5,
			"script": "마지막 3사 저 마서 매력적인 이를",
			"hash": null,
			"sub_hash": "dbdbd980818181ff",
			"usage": false
		},
		{
			"frame_num": 59,
			"img_path": "/home/ubuntu/project/youtube_capture/imgs/4059.jpg.dupli.jpg",
			"time_info": 238.0,
			"script": "목적이 있는 일입니다 우리는 이 일을 하기 위해 태어났으며 이 일을 할",
			"hash": null,
			"sub_hash": "dbdbd980818181ff",
			"usage": false
		},
		{
			"frame_num": 60,
			"img_path": "/home/ubuntu/project/youtube_capture/imgs/4060.jpg.dupli.jpg",
			"time_info": 241.5,
			"script": "때 가장 열중하고",
			"hash": null,
			"sub_hash": "dbdbd980818181ff",
			"usage": false
		},
		{
			"frame_num": 61,
			"img_path": "/home/ubuntu/project/youtube_capture/imgs/4061.jpg",
			"time_info": 245.0,
			"script": "가장 크 반향을 일으킵니다 이 칸에 해당하는 일은 매우 적습니다",
			"hash": null,
			"sub_hash": "b7b78383818181ff",
			"usage": true
		},
		{
			"frame_num": 62,
			"img_path": "/home/ubuntu/project/youtube_capture/imgs/4062.jpg.dupli.jpg",
			"time_info": 249.5,
			"script": "배우라면 최저 리어 절과 공역",
			"hash": null,
			"sub_hash": "b7b78383818181ff",
			"usage": false
		},
		{
			"frame_num": 63,
			"img_path": "/home/ubuntu/project/youtube_capture/imgs/4063.jpg.dupli.jpg",
			"time_info": 253.5,
			"script": "연구원 이라면 연구를 설계하고 진행하기 연구비 지원 바퀴",
			"hash": null,
			"sub_hash": "b7a78383818181ff",
			"usage": false
		},
		{
			"frame_num": 64,
			"img_path": "/home/ubuntu/project/youtube_capture/imgs/4064.jpg",
			"time_info": 259.0,
			"script": "작가라면 글을 쓰고 새로운 아이디어를 되고 소재를 연구하는 것이 되겠죠",
			"hash": null,
			"sub_hash": "bcfca0f8c08081ff",
			"usage": true
		},
		{
			"frame_num": 65,
			"img_path": "/home/ubuntu/project/youtube_capture/imgs/4065.jpg",
			"time_info": 265.0,
			"script": "여러분도 잠시 영상을 멈추고 5분만 시간을 되어 이 표로 작성해 보세요",
			"hash": null,
			"sub_hash": "f9f9f9f9818181f9",
			"usage": true
		},
		{
			"frame_num": 66,
			"img_path": "/home/ubuntu/project/youtube_capture/imgs/4066.jpg",
			"time_info": 270.0,
			"script": "저도 직접 프로 작성해서 이를 나누었던 2",
			"hash": null,
			"sub_hash": "ffffffff818181ff",
			"usage": true
		},
		{
			"frame_num": 67,
			"img_path": "/home/ubuntu/project/youtube_capture/imgs/4067.jpg.dupli.jpg",
			"time_info": 273.5,
			"script": "그거 만으로도 자동 초점 모드를 끄고",
			"hash": null,
			"sub_hash": "ffffffff818181ff",
			"usage": false
		},
		{
			"frame_num": 68,
			"img_path": "/home/ubuntu/project/youtube_capture/imgs/4068.jpg",
			"time_info": 277.0,
			"script": "목적이 내 일에 집중하는 데 큰 도움이 되었습니다",
			"hash": null,
			"sub_hash": "f9ffffff818181ff",
			"usage": true
		},
		{
			"frame_num": 69,
			"img_path": "/home/ubuntu/project/youtube_capture/imgs/4069.jpg",
			"time_info": 281.5,
			"script": "은 트 스스로 물어 보세요 내가 지금 하고 있는 일이 위 4개 영역에서",
			"hash": null,
			"sub_hash": "ffffffff818181ff",
			"usage": true
		},
		{
			"frame_num": 70,
			"img_path": "/home/ubuntu/project/youtube_capture/imgs/4070.jpg.dupli.jpg",
			"time_info": 285.0,
			"script": "어디에 속해 있는지를",
			"hash": null,
			"sub_hash": "ffffffff818181ff",
			"usage": false
		},
		{
			"frame_num": 71,
			"img_path": "/home/ubuntu/project/youtube_capture/imgs/4071.jpg.dupli.jpg",
			"time_info": 288.5,
			"script": "그러면 목적인 n1 필요한 일에 대부분의 시간이 머무르게 끔 조절할 수",
			"hash": null,
			"sub_hash": "ffffffff818181ff",
			"usage": false
		},
		{
			"frame_num": 72,
			"img_path": "/home/ubuntu/project/youtube_capture/imgs/4072.jpg.dupli.jpg",
			"time_info": 292.0,
			"script": "있습니다",
			"hash": null,
			"sub_hash": "ffffffff818181ff",
			"usage": false
		},
		{
			"frame_num": 73,
			"img_path": "/home/ubuntu/project/youtube_capture/imgs/4073.jpg.dupli.jpg",
			"time_info": 295.5,
			"script": "하이퍼 포커스 의 저자는 자각에 종을 메시 올리겠습니다",
			"hash": null,
			"sub_hash": "ffffffff818181ff",
			"usage": false
		},
		{
			"frame_num": 74,
			"img_path": "/home/ubuntu/project/youtube_capture/imgs/4074.jpg",
			"time_info": 300.5,
			"script": "1시간마다 시계 알람 을 설정해서 내가 지금 무엇에 집중하고 있는지",
			"hash": null,
			"sub_hash": "e7e7e7e7818181e7",
			"usage": true
		},
		{
			"frame_num": 75,
			"img_path": "/home/ubuntu/project/youtube_capture/imgs/4075.jpg",
			"time_info": 305.0,
			"script": "자동 조종 상태에 빠져 있는 건 아닌지 확인 햇죠",
			"hash": null,
			"sub_hash": "f7f7f7f7818181ff",
			"usage": true
		},
		{
			"frame_num": 76,
			"img_path": "/home/ubuntu/project/youtube_capture/imgs/4076.jpg.dupli.jpg",
			"time_info": 308.0,
			"script": "이런 확인 작업을 시작하면 처음에는",
			"hash": null,
			"sub_hash": "e7f7f7f7818181ff",
			"usage": false
		},
		{
			"frame_num": 77,
			"img_path": "/home/ubuntu/project/youtube_capture/imgs/4077.jpg",
			"time_info": 311.5,
			"script": "불필요하고 주의를 빼앗는 일에 시간을 쓰고 있는 본인의 모습을 자주",
			"hash": null,
			"sub_hash": "9fffffff818181ff",
			"usage": true
		},
		{
			"frame_num": 78,
			"img_path": "/home/ubuntu/project/youtube_capture/imgs/4078.jpg.dupli.jpg",
			"time_info": 315.0,
			"script": "발견할 수 있습니다",
			"hash": null,
			"sub_hash": "9fffffff818181ff",
			"usage": false
		},
		{
			"frame_num": 79,
			"img_path": "/home/ubuntu/project/youtube_capture/imgs/4079.jpg",
			"time_info": 319.0,
			"script": "괜찮습니다 자책하지 말고 자연스럽게 다시 목적이 4일로 방향을 조절하며",
			"hash": null,
			"sub_hash": "80ffffff818181ff",
			"usage": true
		},
		{
			"frame_num": 80,
			"img_path": "/home/ubuntu/project/youtube_capture/imgs/4080.jpg",
			"time_info": 323.0,
			"script": "됩니다",
			"hash": null,
			"sub_hash": "00ffffffffffffff",
			"usage": true
		},
		{
			"frame_num": 81,
			"img_path": "/home/ubuntu/project/youtube_capture/imgs/4081.jpg",
			"time_info": 325.5,
			"script": "그런데도 계속 주일에 빼앗기고 있다면 어떻게 해야 할까요",
			"hash": null,
			"sub_hash": "80ffffff818181ff",
			"usage": true
		},
		{
			"frame_num": 82,
			"img_path": "/home/ubuntu/project/youtube_capture/imgs/4082.jpg.dupli.jpg",
			"time_info": 327.5,
			"script": "[음악]",
			"hash": null,
			"sub_hash": "80ffffff818181ff",
			"usage": false
		},
		{
			"frame_num": 83,
			"img_path": "/home/ubuntu/project/youtube_capture/imgs/4083.jpg",
			"time_info": 330.0,
			"script": "자극적이거나 매력적인 를 일이 제거하고 차단해야 합니다",
			"hash": null,
			"sub_hash": "02ffffff818181ff",
			"usage": true
		},
		{
			"frame_num": 84,
			"img_path": "/home/ubuntu/project/youtube_capture/imgs/4084.jpg.dupli.jpg",
			"time_info": 332.5,
			"script": "[음악]",
			"hash": null,
			"sub_hash": "02ffffff818181ff",
			"usage": false
		},
		{
			"frame_num": 85,
			"img_path": "/home/ubuntu/project/youtube_capture/imgs/4085.jpg",
			"time_info": 335.5,
			"script": "먼저 가벼운 방법은 스마트폰의 알람을 모두 끄는 것입니다",
			"hash": null,
			"sub_hash": "f3f3f7ff818181ff",
			"usage": true
		},
		{
			"frame_num": 86,
			"img_path": "/home/ubuntu/project/youtube_capture/imgs/4086.jpg.dupli.jpg",
			"time_info": 340.0,
			"script": "카카오톡의 든 인스타그램 이든 은행 어플이 든",
			"hash": null,
			"sub_hash": "f3f3f7ff818181ff",
			"usage": false
		},
		{
			"frame_num": 87,
			"img_path": "/home/ubuntu/project/youtube_capture/imgs/4087.jpg",
			"time_info": 344.5,
			"script": "알람을 모두 꺼 주세요 정말 하이퍼 포커스에 들어가고 싶다면",
			"hash": null,
			"sub_hash": "c3c3cfcf818181df",
			"usage": true
		},
		{
			"frame_num": 88,
			"img_path": "/home/ubuntu/project/youtube_capture/imgs/4088.jpg",
			"time_info": 350.0,
			"script": "비행기 모두를 켜 두거나 스마트폰 r 다른 곳에 두고 일을 시작하세요",
			"hash": null,
			"sub_hash": "1313ffff818181ff",
			"usage": true
		},
		{
			"frame_num": 89,
			"img_path": "/home/ubuntu/project/youtube_capture/imgs/4089.jpg",
			"time_info": 355.0,
			"script": "노트북으로 일한다면 와이파이가 없는 카페로 가서 일하는 것도 좋습니다",
			"hash": null,
			"sub_hash": "b0b0fcfec080c0fc",
			"usage": true
		},
		{
			"frame_num": 90,
			"img_path": "/home/ubuntu/project/youtube_capture/imgs/4090.jpg",
			"time_info": 357.5,
			"script": "[음악]",
			"hash": null,
			"sub_hash": "3030ffff838181ff",
			"usage": true
		},
		{
			"frame_num": 91,
			"img_path": "/home/ubuntu/project/youtube_capture/imgs/4091.jpg.dupli.jpg",
			"time_info": 359.5,
			"script": "인터넷을 완전 댓글 수 없다면 지성 1",
			"hash": null,
			"sub_hash": "3030ffff838181ff",
			"usage": false
		},
		{
			"frame_num": 92,
			"img_path": "/home/ubuntu/project/youtube_capture/imgs/4092.jpg",
			"time_info": 364.0,
			"script": "웹사이트 만들어 하지 못하게 하는 차가 어플을 사용하는 것도 좋습니다",
			"hash": null,
			"sub_hash": "3010ffff818181ff",
			"usage": true
		},
		{
			"frame_num": 93,
			"img_path": "/home/ubuntu/project/youtube_capture/imgs/4093.jpg",
			"time_info": 369.5,
			"script": "자 이제 영상이 끝나면 같이 하이퍼 포커스 에 들어가봅시다",
			"hash": null,
			"sub_hash": "cfcfcfcf818181cf",
			"usage": true
		},
		{
			"frame_num": 94,
			"img_path": "/home/ubuntu/project/youtube_capture/imgs/4094.jpg",
			"time_info": 374.5,
			"script": "목적이 있는 l 필요한 일 중에서 지금 가장 중요한 일 하나를 선택해",
			"hash": null,
			"sub_hash": "dfdfffff818181ff",
			"usage": true
		},
		{
			"frame_num": 95,
			"img_path": "/home/ubuntu/project/youtube_capture/imgs/4095.jpg.dupli.jpg",
			"time_info": 378.0,
			"script": "봅시다",
			"hash": null,
			"sub_hash": "dfdfffff818181ff",
			"usage": false
		},
		{
			"frame_num": 96,
			"img_path": "/home/ubuntu/project/youtube_capture/imgs/4096.jpg.dupli.jpg",
			"time_info": 381.5,
			"script": "이 일을 언제까지 왜 끝내 하는지를 생각한 다음 그 돌을 가지 채 일을",
			"hash": null,
			"sub_hash": "dfdfffff818181ff",
			"usage": false
		},
		{
			"frame_num": 97,
			"img_path": "/home/ubuntu/project/youtube_capture/imgs/4097.jpg.dupli.jpg",
			"time_info": 385.0,
			"script": "시작해 봅시다",
			"hash": null,
			"sub_hash": "dfdfffff818181ff",
			"usage": false
		},
		{
			"frame_num": 98,
			"img_path": "/home/ubuntu/project/youtube_capture/imgs/4098.jpg.dupli.jpg",
			"time_info": 388.5,
			"script": "주의를 끄는 것들은 일이 완전히 차단하고 요",
			"hash": null,
			"sub_hash": "dfdfffff818181ff",
			"usage": false
		},
		{
			"frame_num": 99,
			"img_path": "/home/ubuntu/project/youtube_capture/imgs/4099.jpg",
			"time_info": 391.0,
			"script": "책그림이었습니다 감사합니다",
			"hash": null,
			"sub_hash": "ffffffff818181ff",
			"usage": true
		},
		{
			"frame_num": 100,
			"img_path": "/home/ubuntu/project/youtube_capture/imgs/40100.jpg",
			"time_info": 395.5,
			"script": "[음악]",
			"hash": null,
			"sub_hash": "c3ffe7e7ffff0000",
			"usage": true
		},
		{
			"frame_num": 101,
			"img_path": "/home/ubuntu/project/youtube_capture/imgs/40101.jpg.dupli.jpg",
			"time_info": 401.0,
			"script": "",
			"hash": null,
			"sub_hash": "c3ffe7e7ffff0000",
			"usage": false
		}
	]
}